dynamite_cli/__init__.py
dynamite_cli/dynamo_copy.py
dynamite_cli/main.py
dynamite_cli-0.1.2.dist-info/entry_points.txt
dynamite_cli-0.1.2.dist-info/LICENSE
dynamite_cli-0.1.2.dist-info/WHEEL
dynamite_cli-0.1.2.dist-info/METADATA
dynamite_cli-0.1.2.dist-info/RECORD
