Metadata-Version: 2.1
Name: dynamite-cli
Version: 0.1.2
Summary: 
Home-page: https://github.com/softwarebloat/dynamite-cli
License: MIT
Author: softwarebloat
Author-email: softwarebloat@gmail.com
Requires-Python: >=3.8,<4.0
Classifier: License :: OSI Approved :: MIT License
Classifier: Programming Language :: Python :: 3
Classifier: Programming Language :: Python :: 3.8
Classifier: Programming Language :: Python :: 3.9
Requires-Dist: boto3 (>=1.17.3,<2.0.0)
Requires-Dist: colorama (>=0.4.4,<0.5.0)
Requires-Dist: typer (>=0.3.2,<0.4.0)
Project-URL: Documentation, https://github.com/softwarebloat/dynamite-cli
Project-URL: Repository, https://github.com/softwarebloat/dynamite-cli
